enamlnative_icons.py
enaml_native_icons-1.0.data/data/packages/enaml-native-icons/android/android.iml
enaml_native_icons-1.0.data/data/packages/enaml-native-icons/android/app.iml
enaml_native_icons-1.0.data/data/packages/enaml-native-icons/android/build.gradle
enaml_native_icons-1.0.data/data/packages/enaml-native-icons/android/enaml-native-icons.iml
enaml_native_icons-1.0.data/data/packages/enaml-native-icons/android/gradlew
enaml_native_icons-1.0.data/data/packages/enaml-native-icons/android/gradlew.bat
enaml_native_icons-1.0.data/data/packages/enaml-native-icons/android/local.properties
enaml_native_icons-1.0.data/data/packages/enaml-native-icons/android/proguard-rules.pro
enaml_native_icons-1.0.data/data/packages/enaml-native-icons/android/gradle/wrapper/gradle-wrapper.jar
enaml_native_icons-1.0.data/data/packages/enaml-native-icons/android/gradle/wrapper/gradle-wrapper.properties
enaml_native_icons-1.0.data/data/packages/enaml-native-icons/android/src/main/AndroidManifest.xml
enaml_native_icons-1.0.data/data/packages/enaml-native-icons/android/src/main/java/com/codelv/enamlnative/packages/IconifyPackage.java
enaml_native_icons-1.0.dist-info/DESCRIPTION.rst
enaml_native_icons-1.0.dist-info/METADATA
enaml_native_icons-1.0.dist-info/RECORD
enaml_native_icons-1.0.dist-info/WHEEL
enaml_native_icons-1.0.dist-info/entry_points.txt
enaml_native_icons-1.0.dist-info/metadata.json
enaml_native_icons-1.0.dist-info/top_level.txt
